english2kana/__init__.py
english2kana/configs/config.yaml
english2kana/data_processing/__init__.py
english2kana/data_processing/preprocess.py
english2kana/inference/__init__.py
english2kana/inference/infer.py
english2kana/model/__initi__.py
english2kana/model/attention.py
english2kana/model/build_model.py
english2kana/model/losses.py
english2kana/model/train.py
english2kana-0.1.5.dist-info/LICENSE
english2kana-0.1.5.dist-info/METADATA
english2kana-0.1.5.dist-info/WHEEL
english2kana-0.1.5.dist-info/RECORD
